{
    "version": "https://jsonfeed.org/version/1",
    "title": "浮生偷得半日闲 • All posts by \"编程\" tag",
    "description": "你我皆为星辰之子，每一个细胞都书写着整个宇宙的历史，当你凝视自己，也望见了宇宙的轮廓。",
    "home_page_url": "http://whitebear7396.top",
    "items": [
        {
            "id": "http://whitebear7396.top/2020/08/27/programme/CleanUpWeChatZombieFans%E7%AC%94%E8%AE%B0/",
            "url": "http://whitebear7396.top/2020/08/27/programme/CleanUpWeChatZombieFans%E7%AC%94%E8%AE%B0/",
            "title": "CleanUpWeChatZombieFans笔记",
            "date_published": "2020-08-27T05:20:52.000Z",
            "content_html": "<h1 id=\"目的\"><a href=\"#目的\" class=\"headerlink\" title=\"目的\"></a>目的</h1><p>通过对&lt;清理微信僵尸粉.js&gt;脚本的分析，了解其运行原理，补充相关JS知识点。</p>\n<h1 id=\"第一周\"><a href=\"#第一周\" class=\"headerlink\" title=\"第一周\"></a>第一周</h1><h2 id=\"匿名函数\"><a href=\"#匿名函数\" class=\"headerlink\" title=\"匿名函数\"></a>匿名函数</h2><p>（（）=&gt; {} ）、(function(){})<br>标准的函数，没有赋值给任何变量，没有名字的函数，叫匿名函数.主要是利用函数内的变量作用。避免产生全局变量，影响整体页面环境，增加代码的兼容性。因为没有名字，所以在定义完成就要调用，（（）=&gt; {} ）（），后面的（）是调用运行这个匿名函数的意思.</p>\n",
            "tags": [
                "编程",
                "JaveScript"
            ]
        },
        {
            "id": "http://whitebear7396.top/2020/08/27/programme/JavaScript/%E7%AC%AC1%E5%91%A8/",
            "url": "http://whitebear7396.top/2020/08/27/programme/JavaScript/%E7%AC%AC1%E5%91%A8/",
            "title": "第1周",
            "date_published": "2020-08-27T05:20:52.000Z",
            "content_html": "<h1 id=\"什么是语言\"><a href=\"#什么是语言\" class=\"headerlink\" title=\"什么是语言\"></a>什么是语言</h1><ul>\n<li><p>计算机就是一个由人来控制的机器,人让它干嘛,它就得干嘛。</p>\n</li>\n<li><p>我们要学习的语言就是人和计算机交流的工具，人类通过语言来控制、操作计算机。</p>\n</li>\n<li><p>编程语言和我们说的中文、英文本质上没有区别,只是语法比较特殊。</p>\n</li>\n<li><p>语言的发展:</p>\n<p>–纸带机:机器语言</p>\n<p>–汇编语言:符号语言</p>\n<p>–现代语言:高级语言</p>\n</li>\n</ul>\n<h2 id=\"起源\"><a href=\"#起源\" class=\"headerlink\" title=\"起源\"></a>起源</h2><ul>\n<li><p>JavaScript诞生于1995年,它的出现主要是用于处理网页中的前端验证。</p>\n</li>\n<li><p>所谓的前端验证,就是指检查用户输入的内容是否符合一定的规则。</p>\n</li>\n<li><p>比如:用户名的长度,密码的长度,邮箱的格式等。</p>\n</li>\n</ul>\n<h2 id=\"简史\"><a href=\"#简史\" class=\"headerlink\" title=\"简史\"></a>简史</h2><ul>\n<li>JavaScript是由网景公司发明,起初命名为LiveScript ,后来由于SUN公司的介入更名为了JavaScript.</li>\n<li>1996年微软公司在其最新的IE3浏览器中引入了自己对Javascript的实现JScript.</li>\n<li>于是市面上存在两个版本的JavaScript,一个网景公司的JavaScript和微软的JScript.</li>\n<li>为了确保不同的浏览器上运行的JavaScript标准一致,所以几个公司共同定制了JS的标准名命名为ECMAScript.</li>\n</ul>\n<h2 id=\"时间表\"><a href=\"#时间表\" class=\"headerlink\" title=\"时间表\"></a>时间表</h2><table>\n<thead>\n<tr>\n<th align=\"center\">年份</th>\n<th align=\"center\">事件</th>\n</tr>\n</thead>\n<tbody><tr>\n<td align=\"center\">1995</td>\n<td align=\"center\">网景公司开发了JavaScript</td>\n</tr>\n<tr>\n<td align=\"center\">1996</td>\n<td align=\"center\">微软发布了和JavaScript兼容的JScript</td>\n</tr>\n<tr>\n<td align=\"center\">1997</td>\n<td align=\"center\">ECMAScript 第1版 ( ECMA-262)</td>\n</tr>\n<tr>\n<td align=\"center\">1998</td>\n<td align=\"center\">ECMASCript第2版、DOM Level1的制定、新型语言DHTML登场</td>\n</tr>\n<tr>\n<td align=\"center\">1999</td>\n<td align=\"center\">ECMAScript第3版</td>\n</tr>\n<tr>\n<td align=\"center\">2000</td>\n<td align=\"center\">DOM Level2的制定</td>\n</tr>\n<tr>\n<td align=\"center\">2002</td>\n<td align=\"center\">ISO/ IEC 16262:2002的确立</td>\n</tr>\n<tr>\n<td align=\"center\">2004</td>\n<td align=\"center\">DOM Level3的制定</td>\n</tr>\n<tr>\n<td align=\"center\">2005</td>\n<td align=\"center\">新型语言AJAX登场</td>\n</tr>\n<tr>\n<td align=\"center\">2009</td>\n<td align=\"center\">ECMAScript第5版、新型语言HTML5登场</td>\n</tr>\n</tbody></table>\n<h1 id=\"实现\"><a href=\"#实现\" class=\"headerlink\" title=\"实现\"></a>实现</h1><table>\n<thead>\n<tr>\n<th align=\"center\">浏览器</th>\n<th>Javascript实现方式</th>\n</tr>\n</thead>\n<tbody><tr>\n<td align=\"center\">FireFox</td>\n<td>SpiderMonkey</td>\n</tr>\n<tr>\n<td align=\"center\">Internet Explorer</td>\n<td>JScript/Chakra</td>\n</tr>\n<tr>\n<td align=\"center\">Safari</td>\n<td>JavaScriptCore</td>\n</tr>\n<tr>\n<td align=\"center\">Chrome</td>\n<td>v8</td>\n</tr>\n<tr>\n<td align=\"center\">Carakan</td>\n<td>Carakan</td>\n</tr>\n</tbody></table>\n<ul>\n<li>我们已经知道ECMAScript是JavaScript标准,所以一般情况下这两个词我们认为是一个意思。</li>\n<li>但是实际上JavaScript的含义却要更大一些。</li>\n<li>一个完整的JavaScript实现应该由以下三个部分构成:</li>\n</ul>\n<h2 id=\"特点\"><a href=\"#特点\" class=\"headerlink\" title=\"特点\"></a>特点</h2><p>JS的特点</p>\n<ul>\n<li>解释型语言</li>\n<li>类似于C和Java的语法结构</li>\n<li>动态语言</li>\n<li>基于原型的面向对象</li>\n</ul>\n<h1 id=\"实操\"><a href=\"#实操\" class=\"headerlink\" title=\"实操\"></a>实操</h1><p>alert()//控制浏览器弹出一个警告框</p>\n<p>document. write ()//让计算机在页面中输出一个内容</p>\n<p>console.1og()//向控制台输出一个内容</p>\n",
            "tags": [
                "编程",
                "JaveScript"
            ]
        },
        {
            "id": "http://whitebear7396.top/2020/08/27/programme/JavaScript/%E7%AC%AC2%E5%91%A8/",
            "url": "http://whitebear7396.top/2020/08/27/programme/JavaScript/%E7%AC%AC2%E5%91%A8/",
            "title": "第2周",
            "date_published": "2020-08-27T05:20:52.000Z",
            "content_html": "<h1 id=\"代码位置\"><a href=\"#代码位置\" class=\"headerlink\" title=\"代码位置\"></a>代码位置</h1><h2 id=\"放置于网页-lt-head-head-gt-之内-推荐\"><a href=\"#放置于网页-lt-head-head-gt-之内-推荐\" class=\"headerlink\" title=\"放置于网页&lt;head/head&gt;之内(推荐)\"></a>放置于网页&lt;head/head&gt;之内(推荐)</h2><p>例如：可以将js代码编写到script标签</p>\n<figure class=\"highlight js\"><table><tr><td class=\"gutter\"><pre><span class=\"line\">1</span><br><span class=\"line\">2</span><br><span class=\"line\">3</span><br><span class=\"line\">4</span><br><span class=\"line\">5</span><br><span class=\"line\">6</span><br><span class=\"line\">7</span><br><span class=\"line\">8</span><br><span class=\"line\">9</span><br><span class=\"line\">10</span><br><span class=\"line\">11</span><br><span class=\"line\">12</span><br><span class=\"line\">13</span><br><span class=\"line\">14</span><br></pre></td><td class=\"code\"><pre><span class=\"line\">&lt;!DOCTYPE html&gt;</span><br><span class=\"line\">&lt;html&gt;</span><br><span class=\"line\">    &lt;head&gt;</span><br><span class=\"line\">        &lt;meta charset=<span class=\"string\">&quot;UTF-8&quot;</span>&gt;</span><br><span class=\"line\">        &lt;title&gt;&lt;/title&gt;</span><br><span class=\"line\">        &lt;!--JS代码需要编写到Script标签中--&gt;</span><br><span class=\"line\">        &lt;script type=<span class=\"string\">&quot;text/javascript&quot;</span>&gt;</span><br><span class=\"line\">        </span><br><span class=\"line\">         </span><br><span class=\"line\">        &lt;/script&gt;</span><br><span class=\"line\">    &lt;/head&gt;</span><br><span class=\"line\">    &lt;body&gt;</span><br><span class=\"line\">    &lt;/body&gt;</span><br><span class=\"line\">&lt;/html&gt;</span><br></pre></td></tr></table></figure>\n\n<p>例如：以将js代码编写到外部js文件中,然后通过script标签引，写到外部文件中可以在不同的页面中同时引用,也可以利用到浏览器的缓存机制，<strong>推荐使用的方式</strong></p>\n<figure class=\"highlight js\"><table><tr><td class=\"gutter\"><pre><span class=\"line\">1</span><br><span class=\"line\">2</span><br><span class=\"line\">3</span><br><span class=\"line\">4</span><br><span class=\"line\">5</span><br><span class=\"line\">6</span><br><span class=\"line\">7</span><br><span class=\"line\">8</span><br><span class=\"line\">9</span><br><span class=\"line\">10</span><br><span class=\"line\">11</span><br><span class=\"line\">12</span><br></pre></td><td class=\"code\"><pre><span class=\"line\">&lt;!DOCTYPE html&gt;</span><br><span class=\"line\">&lt;html&gt;</span><br><span class=\"line\">    &lt;head&gt;</span><br><span class=\"line\">        &lt;meta charset=<span class=\"string\">&quot;UTF-8&quot;</span>&gt;</span><br><span class=\"line\">        &lt;title&gt;&lt;/title&gt;</span><br><span class=\"line\">        &lt;!--JS代码需要编写到Script标签中--&gt;</span><br><span class=\"line\">        &lt;script type=<span class=\"string\">&quot;text/javascript&quot;</span> src=<span class=\"string\">&quot;js/script.js&quot;</span>&gt;&lt;/script&gt;</span><br><span class=\"line\">        &lt;/script&gt;</span><br><span class=\"line\">    &lt;/head&gt;</span><br><span class=\"line\">    &lt;body&gt;</span><br><span class=\"line\">    &lt;/body&gt;</span><br><span class=\"line\">&lt;/html&gt;</span><br></pre></td></tr></table></figure>\n\n\n\n<h2 id=\"放置于网页-lt-body-body-gt-之内（不推荐）\"><a href=\"#放置于网页-lt-body-body-gt-之内（不推荐）\" class=\"headerlink\" title=\"放置于网页&lt;body/body&gt;之内（不推荐）\"></a>放置于网页&lt;body/body&gt;之内（不推荐）</h2><p>例如：可以将js代码编写到标签 onclick属性中，1当我们点击按钮时, Js代码才会执行</p>\n<figure class=\"highlight js\"><table><tr><td class=\"gutter\"><pre><span class=\"line\">1</span><br><span class=\"line\">2</span><br><span class=\"line\">3</span><br><span class=\"line\">4</span><br><span class=\"line\">5</span><br><span class=\"line\">6</span><br><span class=\"line\">7</span><br><span class=\"line\">8</span><br><span class=\"line\">9</span><br><span class=\"line\">10</span><br></pre></td><td class=\"code\"><pre><span class=\"line\">&lt;!DOCTYPE html&gt;</span><br><span class=\"line\">&lt;html&gt;</span><br><span class=\"line\">    &lt;head&gt;</span><br><span class=\"line\">        &lt;meta charset=<span class=\"string\">&quot;UTF-8&quot;</span>&gt;</span><br><span class=\"line\">        &lt;title&gt;&lt;/title&gt;</span><br><span class=\"line\">    &lt;/head&gt;</span><br><span class=\"line\">    &lt;body&gt;</span><br><span class=\"line\">          &lt;button onclick=<span class=\"string\">&quot;alert(&#x27;11111&#x27;);&quot;</span>&gt;点我一下 &lt;/button&gt;  </span><br><span class=\"line\">    &lt;/body&gt;</span><br><span class=\"line\">&lt;/html&gt;</span><br></pre></td></tr></table></figure>\n\n<p>例如：,可以将js代码写在超链接的href属性中,这样当点击超链接时,会执行js代码</p>\n<figure class=\"highlight js\"><table><tr><td class=\"gutter\"><pre><span class=\"line\">1</span><br><span class=\"line\">2</span><br><span class=\"line\">3</span><br><span class=\"line\">4</span><br><span class=\"line\">5</span><br><span class=\"line\">6</span><br><span class=\"line\">7</span><br><span class=\"line\">8</span><br><span class=\"line\">9</span><br><span class=\"line\">10</span><br></pre></td><td class=\"code\"><pre><span class=\"line\">&lt;!DOCTYPE html&gt;</span><br><span class=\"line\">&lt;html&gt;</span><br><span class=\"line\">    &lt;head&gt;</span><br><span class=\"line\">        &lt;meta charset=<span class=\"string\">&quot;UTF-8&quot;</span>&gt;</span><br><span class=\"line\">        &lt;title&gt;&lt;/title&gt;</span><br><span class=\"line\">    &lt;/head&gt;</span><br><span class=\"line\">    &lt;body&gt;</span><br><span class=\"line\">          &lt;a href=<span class=\"string\">&quot;javascript: alert(&#x27;2222222&#x27;);&quot;</span>&gt;网页显示的文本&lt;/a&gt;</span><br><span class=\"line\">    &lt;/body&gt;</span><br><span class=\"line\">&lt;/html&gt;</span><br></pre></td></tr></table></figure>\n\n<h1 id=\"基本语法\"><a href=\"#基本语法\" class=\"headerlink\" title=\"基本语法\"></a>基本语法</h1><h2 id=\"注释\"><a href=\"#注释\" class=\"headerlink\" title=\"注释\"></a>注释</h2><figure class=\"highlight js\"><table><tr><td class=\"gutter\"><pre><span class=\"line\">1</span><br></pre></td><td class=\"code\"><pre><span class=\"line\"><span class=\"comment\">//单行注释    </span></span><br></pre></td></tr></table></figure>\n\n<figure class=\"highlight js\"><table><tr><td class=\"gutter\"><pre><span class=\"line\">1</span><br><span class=\"line\">2</span><br><span class=\"line\">3</span><br></pre></td><td class=\"code\"><pre><span class=\"line\"><span class=\"comment\">/*</span></span><br><span class=\"line\"><span class=\"comment\">*多行注释   *号有没有没关系，为了美观</span></span><br><span class=\"line\"><span class=\"comment\">*/</span></span><br></pre></td></tr></table></figure>\n\n<h2 id=\"大小写\"><a href=\"#大小写\" class=\"headerlink\" title=\"大小写\"></a>大小写</h2><figure class=\"highlight js\"><table><tr><td class=\"gutter\"><pre><span class=\"line\">1</span><br><span class=\"line\">2</span><br></pre></td><td class=\"code\"><pre><span class=\"line\">alert(<span class=\"string\">&quot;可运行&quot;</span>);</span><br><span class=\"line\">Alert(<span class=\"string\">&quot;不可运行&quot;</span>);</span><br></pre></td></tr></table></figure>\n\n<h2 id=\"以-结尾\"><a href=\"#以-结尾\" class=\"headerlink\" title=\"以(;)结尾\"></a>以(;)结尾</h2><ul>\n<li>如果不写分号,浏览器会自动添加,但是会消耗一些系统资源,</li>\n<li>有些时候,浏览器会加错分号</li>\n</ul>\n<h2 id=\"空格和换行\"><a href=\"#空格和换行\" class=\"headerlink\" title=\"空格和换行\"></a>空格和换行</h2><ul>\n<li>js中会忽略多个空格和换行,所以我们可以利用空格和换行对代码进行格式化（美观）</li>\n</ul>\n<h2 id=\"字面量和变量\"><a href=\"#字面量和变量\" class=\"headerlink\" title=\"字面量和变量\"></a>字面量和变量</h2><h3 id=\"字面量\"><a href=\"#字面量\" class=\"headerlink\" title=\"字面量\"></a>字面量</h3><p>都是一些不可改变的值</p>\n<p>比如：12345</p>\n<p>字面量都是可以直接使用,但是我们一般都不会直接使用字面量</p>\n<h3 id=\"变量\"><a href=\"#变量\" class=\"headerlink\" title=\"变量\"></a>变量</h3><p>变量可以用来保存字面量,而且变量的值是可以任意改变的</p>\n<p>变量更加方便我们使用,所以在开发中都是通过变量去保存一个字面量,而很少直接使用字面量</p>\n<h3 id=\"赋值\"><a href=\"#赋值\" class=\"headerlink\" title=\"赋值\"></a>赋值</h3><p>通过var为变量赋值</p>\n<figure class=\"highlight js\"><table><tr><td class=\"gutter\"><pre><span class=\"line\">1</span><br></pre></td><td class=\"code\"><pre><span class=\"line\"><span class=\"keyword\">var</span> b = <span class=\"number\">100</span></span><br></pre></td></tr></table></figure>\n\n<p>通过let为变量赋值</p>\n<figure class=\"highlight js\"><table><tr><td class=\"gutter\"><pre><span class=\"line\">1</span><br></pre></td><td class=\"code\"><pre><span class=\"line\"><span class=\"keyword\">let</span> b = <span class=\"number\">100</span></span><br></pre></td></tr></table></figure>\n\n<h2 id=\"标识符\"><a href=\"#标识符\" class=\"headerlink\" title=\"标识符\"></a>标识符</h2><ul>\n<li><p>在JS中所有的可以由我们自主名的都可以称为是标识符</p>\n</li>\n<li><p>例如:变量名、函数名、属性名都属于标识符</p>\n</li>\n<li><p>命名一个标识符时需要遵守如下的规则:</p>\n<ul>\n<li><p>标识符中可以含有字母、数字、_、$</p>\n</li>\n<li><p>标识符不能以数字开头</p>\n</li>\n<li><p>标识符不能是ES中的关键字或保留字</p>\n</li>\n<li><p>标识符一般都采用驼峰命名法</p>\n<p>首字母小写,每个单词的开头字母大写,其余字母小写</p>\n<p>helloworld     xxxYyyzzz</p>\n</li>\n</ul>\n</li>\n<li><p>JS底层保存标识符时实际上是采用的Unicode编码</p>\n<p>所以理论上讲,所有的utf-8中含有的内容都可以作为标识符</p>\n<p>中文可以用，但是没必要，不推荐使用。</p>\n</li>\n</ul>\n<h3 id=\"关键词\"><a href=\"#关键词\" class=\"headerlink\" title=\"关键词\"></a>关键词</h3><table>\n<thead>\n<tr>\n<th></th>\n<th></th>\n<th></th>\n<th></th>\n<th></th>\n</tr>\n</thead>\n<tbody><tr>\n<td>break</td>\n<td>do</td>\n<td>instanceof</td>\n<td>typeof</td>\n<td>case</td>\n</tr>\n<tr>\n<td>else</td>\n<td>new</td>\n<td>var</td>\n<td>catch</td>\n<td>finally</td>\n</tr>\n<tr>\n<td>return</td>\n<td>void</td>\n<td>continue</td>\n<td>for</td>\n<td>switch</td>\n</tr>\n<tr>\n<td>while</td>\n<td>defaul</td>\n<td>if</td>\n<td>throw</td>\n<td>delete</td>\n</tr>\n<tr>\n<td>in</td>\n<td>try</td>\n<td>function</td>\n<td>this</td>\n<td>with</td>\n</tr>\n<tr>\n<td>debugger</td>\n<td>false</td>\n<td>true</td>\n<td>null</td>\n<td></td>\n</tr>\n</tbody></table>\n<h3 id=\"保留字符\"><a href=\"#保留字符\" class=\"headerlink\" title=\"保留字符\"></a>保留字符</h3><table>\n<thead>\n<tr>\n<th></th>\n<th></th>\n<th></th>\n<th></th>\n<th></th>\n</tr>\n</thead>\n<tbody><tr>\n<td>class</td>\n<td>interface</td>\n<td>package</td>\n<td>private</td>\n<td>public</td>\n</tr>\n<tr>\n<td>yield</td>\n<td>enum</td>\n<td>extends</td>\n<td>let</td>\n<td>implements</td>\n</tr>\n<tr>\n<td>export</td>\n<td>import</td>\n<td>super</td>\n<td>protected</td>\n<td>statio</td>\n</tr>\n<tr>\n<td>const</td>\n<td></td>\n<td></td>\n<td></td>\n<td></td>\n</tr>\n<tr>\n<td></td>\n<td></td>\n<td></td>\n<td></td>\n<td></td>\n</tr>\n</tbody></table>\n<h2 id=\"数据类型\"><a href=\"#数据类型\" class=\"headerlink\" title=\"数据类型\"></a>数据类型</h2><p>string  Number  Boolean  Null  Undefined  属于基本数据类型</p>\n<p>Object属于引用数据类型</p>\n<h3 id=\"String字符串\"><a href=\"#String字符串\" class=\"headerlink\" title=\"String字符串\"></a>String字符串</h3><ul>\n<li><p>在JS中字符串需要使用引号引起来</p>\n</li>\n<li><p>使用双引号或单引号都可以,但是不要混着用</p>\n</li>\n<li><p>引号不能嵌套,双引号不能放双引号,单引号不能放单引号</p>\n<p>例如</p>\n<figure class=\"highlight js\"><table><tr><td class=\"gutter\"><pre><span class=\"line\">1</span><br><span class=\"line\">2</span><br><span class=\"line\">3</span><br></pre></td><td class=\"code\"><pre><span class=\"line\"><span class=\"keyword\">var</span> str = <span class=\"string\">&#x27;hello&#x27;</span>;</span><br><span class=\"line\">str= <span class=\"string\">&#x27;我说:&quot;今天天气真不错! &quot;&#x27;</span></span><br><span class=\"line\"><span class=\"built_in\">console</span>.log(str);</span><br></pre></td></tr></table></figure>\n\n<p>在字符串中我们可以使用\\作为转义字符</p>\n<ul>\n<li>当表示一些特殊符号时可以使用\\进行转义</li>\n<li>&quot;表示”</li>\n<li>&#39;表示’</li>\n<li>\\n表示换行</li>\n<li>\\t制表符</li>\n<li>\\表示\\</li>\n</ul>\n</li>\n</ul>\n<h3 id=\"Number数值\"><a href=\"#Number数值\" class=\"headerlink\" title=\"Number数值\"></a>Number数值</h3><p>在JS中所有的数值都是Numper类型</p>\n<p>包括整数和浮点数(小数)</p>\n<p>js中可以表示的数字的最大值</p>\n<ul>\n<li><p>Number.MAX_VALUE      =      1.7976931348623157e+308</p>\n</li>\n<li><p>Number.MIN VALUE        =      5e-324</p>\n</li>\n</ul>\n<p>如果使用Number表示的数字超过了最大值,则会返回一个</p>\n<ul>\n<li>Infinity表示正无穷</li>\n<li>-Infinity表示负无穷</li>\n</ul>\n<p>使用typeof检查Infinity也会返回number</p>\n<ul>\n<li><p>NaN是一个特殊的数字,表示Not A Number</p>\n</li>\n<li><p>使用typeof检查一个NaNt会返回number</p>\n</li>\n</ul>\n<p>可以使用一个运算符typeof来检查一个变量的类型: typeof 变量</p>\n<ul>\n<li><p>检查字符串时,会返回string</p>\n</li>\n<li><p>检查数值时,会返回number</p>\n</li>\n</ul>\n<p>如果使用JS进行浮点运算可能得到一个不精确的结果所以千万不要使用JS进存对精确度要求比较高的运算</p>\n<h3 id=\"Boolean布尔值\"><a href=\"#Boolean布尔值\" class=\"headerlink\" title=\"Boolean布尔值\"></a>Boolean布尔值</h3><p>布尔值只有两个,主要用来做逻辑判断</p>\n<ul>\n<li>true-表示真</li>\n<li>false-表示假</li>\n</ul>\n<p>用typeof检查—个布尔时, 返回boolean</p>\n<h3 id=\"Null（空值）\"><a href=\"#Null（空值）\" class=\"headerlink\" title=\"Null（空值）\"></a>Null（空值）</h3><p>Nu11类型的值只有一个,就是null</p>\n<p>nu1l这个值专门用来表示一个为空的对象</p>\n<p>使用typeof检查一个nul1值时,会返回object</p>\n<h3 id=\"Undefined（未定义）\"><a href=\"#Undefined（未定义）\" class=\"headerlink\" title=\"Undefined（未定义）\"></a>Undefined（未定义）</h3><p>Undefined (未定义)类型的值只有一个, 就undefind</p>\n<p>当声明一个变量,但是并不给变量赋值时,它的值就是undefind</p>\n<p>使用typeof检查一个undefined时，会返回undefined</p>\n<h3 id=\"Object对象\"><a href=\"#Object对象\" class=\"headerlink\" title=\"Object对象\"></a>Object对象</h3>",
            "tags": [
                "编程",
                "JaveScript"
            ]
        },
        {
            "id": "http://whitebear7396.top/2020/08/27/programme/Python/JS%E7%AC%AC1%E5%91%A8/",
            "url": "http://whitebear7396.top/2020/08/27/programme/Python/JS%E7%AC%AC1%E5%91%A8/",
            "title": "第1周",
            "date_published": "2020-08-27T05:20:52.000Z",
            "content_html": "<h1 id=\"什么是语言\"><a href=\"#什么是语言\" class=\"headerlink\" title=\"什么是语言\"></a>什么是语言</h1><ul>\n<li><p>计算机就是一个由人来控制的机器,人让它干嘛,它就得干嘛。</p>\n</li>\n<li><p>我们要学习的语言就是人和计算机交流的工具，人类通过语言来控制、操作计算机。</p>\n</li>\n<li><p>编程语言和我们说的中文、英文本质上没有区别,只是语法比较特殊。</p>\n</li>\n<li><p>语言的发展:</p>\n<p>–纸带机:机器语言</p>\n<p>–汇编语言:符号语言</p>\n<p>–现代语言:高级语言</p>\n</li>\n</ul>\n<h2 id=\"起源\"><a href=\"#起源\" class=\"headerlink\" title=\"起源\"></a>起源</h2><ul>\n<li><p>JavaScript诞生于1995年,它的出现主要是用于处理网页中的前端验证。</p>\n</li>\n<li><p>所谓的前端验证,就是指检查用户输入的内容是否符合一定的规则。</p>\n</li>\n<li><p>比如:用户名的长度,密码的长度,邮箱的格式等。</p>\n</li>\n</ul>\n<h2 id=\"简史\"><a href=\"#简史\" class=\"headerlink\" title=\"简史\"></a>简史</h2><ul>\n<li>JavaScript是由网景公司发明,起初命名为LiveScript ,后来由于SUN公司的介入更名为了JavaScript.</li>\n<li>1996年微软公司在其最新的IE3浏览器中引入了自己对Javascript的实现JScript.</li>\n<li>于是市面上存在两个版本的JavaScript,一个网景公司的JavaScript和微软的JScript.</li>\n<li>为了确保不同的浏览器上运行的JavaScript标准一致,所以几个公司共同定制了JS的标准名命名为ECMAScript.</li>\n</ul>\n<h2 id=\"时间表\"><a href=\"#时间表\" class=\"headerlink\" title=\"时间表\"></a>时间表</h2><table>\n<thead>\n<tr>\n<th align=\"center\">年份</th>\n<th align=\"center\">事件</th>\n</tr>\n</thead>\n<tbody><tr>\n<td align=\"center\">1995</td>\n<td align=\"center\">网景公司开发了JavaScript</td>\n</tr>\n<tr>\n<td align=\"center\">1996</td>\n<td align=\"center\">微软发布了和JavaScript兼容的JScript</td>\n</tr>\n<tr>\n<td align=\"center\">1997</td>\n<td align=\"center\">ECMAScript 第1版 ( ECMA-262)</td>\n</tr>\n<tr>\n<td align=\"center\">1998</td>\n<td align=\"center\">ECMASCript第2版、DOM Level1的制定、新型语言DHTML登场</td>\n</tr>\n<tr>\n<td align=\"center\">1999</td>\n<td align=\"center\">ECMAScript第3版</td>\n</tr>\n<tr>\n<td align=\"center\">2000</td>\n<td align=\"center\">DOM Level2的制定</td>\n</tr>\n<tr>\n<td align=\"center\">2002</td>\n<td align=\"center\">ISO/ IEC 16262:2002的确立</td>\n</tr>\n<tr>\n<td align=\"center\">2004</td>\n<td align=\"center\">DOM Level3的制定</td>\n</tr>\n<tr>\n<td align=\"center\">2005</td>\n<td align=\"center\">新型语言AJAX登场</td>\n</tr>\n<tr>\n<td align=\"center\">2009</td>\n<td align=\"center\">ECMAScript第5版、新型语言HTML5登场</td>\n</tr>\n</tbody></table>\n<h1 id=\"实现\"><a href=\"#实现\" class=\"headerlink\" title=\"实现\"></a>实现</h1><table>\n<thead>\n<tr>\n<th align=\"center\">浏览器</th>\n<th>Javascript实现方式</th>\n</tr>\n</thead>\n<tbody><tr>\n<td align=\"center\">FireFox</td>\n<td>SpiderMonkey</td>\n</tr>\n<tr>\n<td align=\"center\">Internet Explorer</td>\n<td>JScript/Chakra</td>\n</tr>\n<tr>\n<td align=\"center\">Safari</td>\n<td>JavaScriptCore</td>\n</tr>\n<tr>\n<td align=\"center\">Chrome</td>\n<td>v8</td>\n</tr>\n<tr>\n<td align=\"center\">Carakan</td>\n<td>Carakan</td>\n</tr>\n</tbody></table>\n<ul>\n<li>我们已经知道ECMAScript是JavaScript标准,所以一般情况下这两个词我们认为是一个意思。</li>\n<li>但是实际上JavaScript的含义却要更大一些。</li>\n<li>一个完整的JavaScript实现应该由以下三个部分构成:</li>\n</ul>\n<h2 id=\"特点\"><a href=\"#特点\" class=\"headerlink\" title=\"特点\"></a>特点</h2><p>JS的特点</p>\n<ul>\n<li>解释型语言</li>\n<li>类似于C和Java的语法结构</li>\n<li>动态语言</li>\n<li>基于原型的面向对象</li>\n</ul>\n<h1 id=\"实操\"><a href=\"#实操\" class=\"headerlink\" title=\"实操\"></a>实操</h1><p>alert()//控制浏览器弹出一个警告框</p>\n<p>document. write ()//让计算机在页面中输出一个内容</p>\n<p>console.1og()//向控制台输出一个内容</p>\n",
            "tags": [
                "编程",
                "Python"
            ]
        },
        {
            "id": "http://whitebear7396.top/2020/08/27/programme/Python/%E7%AC%AC1%E5%91%A8/",
            "url": "http://whitebear7396.top/2020/08/27/programme/Python/%E7%AC%AC1%E5%91%A8/",
            "title": "第1周",
            "date_published": "2020-08-27T05:20:52.000Z",
            "content_html": "<h1 id=\"待开始\"><a href=\"#待开始\" class=\"headerlink\" title=\"待开始\"></a>待开始</h1>",
            "tags": [
                "编程",
                "Python"
            ]
        }
    ]
}